cortado/__init__.py
cortado/abstractboolvariate.py
cortado/abstractcovariate.py
cortado/abstractfactor.py
cortado/abstractslicer.py
cortado/boolvariate.py
cortado/cachedcovariate.py
cortado/cachedfactor.py
cortado/chunk.py
cortado/constfactor.py
cortado/consts.py
cortado/covariate.py
cortado/cutcovfactor.py
cortado/dataframe.py
cortado/factor.py
cortado/fileslicer.py
cortado/funcslicer.py
cortado/logistic.py
cortado/nfactorslicer.py
cortado/parsefactorcovariate.py
cortado/seq.py
cortado/split.py
cortado/tree.py
cortado/vectorslicer.py
cortado-1.0rc3.dist-info/LICENSE
cortado-1.0rc3.dist-info/METADATA
cortado-1.0rc3.dist-info/WHEEL
cortado-1.0rc3.dist-info/top_level.txt
cortado-1.0rc3.dist-info/RECORD
