Metadata-Version: 2.1
Name: cortado
Version: 1.0rc3
Summary: High performance ML library with ultra fast XGBoost implementation in pure Python
Home-page: https://github.com/Statfactory/cortado
Author: Adam Mlocek
License: MIT
Platform: UNKNOWN
Requires-Dist: numpy
Requires-Dist: numba
Requires-Dist: pandas
